nonebot_plugin_callapi-0.3.0.dist-info/METADATA
nonebot_plugin_callapi-0.3.0.dist-info/WHEEL
nonebot_plugin_callapi-0.3.0.dist-info/entry_points.txt
nonebot_plugin_callapi-0.3.0.dist-info/licenses/LICENSE
nonebot_plugin_callapi/__init__.py
nonebot_plugin_callapi/__main__.py
nonebot_plugin_callapi/config.py
nonebot_plugin_callapi-0.3.0.dist-info/RECORD
