Metadata-Version: 2.1
Name: nonebot-plugin-callapi
Version: 0.3.0
Summary: Use bot command to call its API
Author-Email: student_2333 <lgc2333@126.com>
License: MIT
Project-URL: homepage, https://github.com/lgc-NB2Dev/nonebot-plugin-callapi
Requires-Python: <4.0,>=3.9
Requires-Dist: nonebot2>=2.3.1
Requires-Dist: nonebot-plugin-alconna>=0.48.0
Requires-Dist: Pygments>=2.18.0
Requires-Dist: pil-utils>=0.2.1
Requires-Dist: cookit[pyd]>=0.8.1
